docbuddy/__init__.py
docbuddy-0.1.5.dist-info/METADATA
docbuddy-0.1.5.dist-info/WHEEL
docbuddy-0.1.5.dist-info/top_level.txt
docbuddy-0.1.5.dist-info/RECORD
