Metadata-Version: 2.4
Name: docbuddy
Version: 0.1.5
Summary: Deprecated: Use ask-docs instead
Home-page: https://github.com/yourusername/docbuddy
Author: Your Name
Author-email: your.email@example.com
Classifier: Development Status :: 7 - Inactive
Classifier: Intended Audience :: Developers
Classifier: Programming Language :: Python :: 3
Classifier: Programming Language :: Python :: 3.6
Classifier: Programming Language :: Python :: 3.7
Classifier: Programming Language :: Python :: 3.8
Classifier: Programming Language :: Python :: 3.9
Classifier: Programming Language :: Python :: 3.10
Classifier: Topic :: Software Development :: Libraries
Requires-Dist: ask-docs>=0.1.0
Dynamic: author
Dynamic: author-email
Dynamic: classifier
Dynamic: description
Dynamic: description-content-type
Dynamic: home-page
Dynamic: requires-dist
Dynamic: summary
